scconfluence/__init__.py
scconfluence/base_module.py
scconfluence/dataset_utils.py
scconfluence/distributions.py
scconfluence/model.py
scconfluence/nn.py
scconfluence/unimodal.py
scconfluence-0.1.1.dist-info/METADATA
scconfluence-0.1.1.dist-info/WHEEL
scconfluence-0.1.1.dist-info/RECORD
