Metadata-Version: 2.1
Name: scconfluence
Version: 0.1.1
Summary: scConfluence is a novel diagonal integration method combining uncoupled autoencoders and Optimal Transport on single-cell data.
License: GPL-3.0-only
Author: jules-samaran
Author-email: jules.samaran@pasteur.fr
Requires-Python: >=3.10,<4.0
Classifier: License :: OSI Approved :: GNU General Public License v3 (GPLv3)
Classifier: Programming Language :: Python :: 3
Classifier: Programming Language :: Python :: 3.10
Classifier: Programming Language :: Python :: 3.11
Classifier: Programming Language :: Python :: 3.12
Requires-Dist: furo[docsbuild] (>=2022.12.7,<2023.0.0)
Requires-Dist: geomloss (>=0.2,<0.3)
Requires-Dist: louvain (>=0.8.2,<0.9.0)
Requires-Dist: mudata (>=0.2.1,<0.3.0)
Requires-Dist: muon (>=0.1.0,<0.2.0)
Requires-Dist: nbsphinx[docsbuild] (>=0.8.12,<0.9.0)
Requires-Dist: numpy (>=1.26.4,<2.0.0)
Requires-Dist: pot (>=0.9.1,<0.10.0)
Requires-Dist: pytorch-lightning (>=2.0.0,<3.0.0)
Requires-Dist: scanpy (>=1.0.0,<2.0.0)
Requires-Dist: scikit-misc (>=0.1.4,<0.2.0)
Requires-Dist: tensorboard (>=2.12.0,<3.0.0)
Requires-Dist: torch (>=2.0.0,<3.0.0)
